aws_mfa_login-1.0.1.dist-info/DESCRIPTION.rst
aws_mfa_login-1.0.1.dist-info/METADATA
aws_mfa_login-1.0.1.dist-info/RECORD
aws_mfa_login-1.0.1.dist-info/WHEEL
aws_mfa_login-1.0.1.dist-info/entry_points.txt
aws_mfa_login-1.0.1.dist-info/metadata.json
aws_mfa_login-1.0.1.dist-info/top_level.txt
wrapp/aws/__init__.py
wrapp/aws/mfa.py
