Metadata-Version: 2.0
Name: aws-mfa-login
Version: 1.0.1
Summary: Generates environment variables for MFA auth against AWS CLI. Python 3.3+.
Home-page: https://github.com/wrapp/aws-mfa-login
Author: Joakim Lundborg, Fredrik Håård
Author-email: joakim.lundborg@wrapp.com, fredrik@metallapan.se
License: MIT
Keywords: aws mfa cli
Platform: UNKNOWN
Classifier: Development Status :: 5 - Production/Stable
Classifier: Intended Audience :: Developers
Classifier: License :: Freely Distributable
Classifier: License :: OSI Approved :: MIT License
Classifier: Operating System :: OS Independent
Classifier: Programming Language :: Python :: 3
Classifier: Programming Language :: Python :: 3.3
